genai_processors/.gitignore
genai_processors/CONTRIBUTING.md
genai_processors/README.md
genai_processors/README.pypi.md
genai_processors/__init__.py
genai_processors/cache.py
genai_processors/cache_base.py
genai_processors/content_api.py
genai_processors/context.py
genai_processors/debug.py
genai_processors/map_processor.py
genai_processors/mime_types.py
genai_processors/processor.py
genai_processors/pyproject.toml
genai_processors/sql_cache.py
genai_processors/streams.py
genai_processors/switch.py
genai_processors/tool_utils.py
genai_processors/.github/workflows/python-tests.yml
genai_processors/contrib/README.md
genai_processors/contrib/__init__.py
genai_processors/contrib/langchain_model.py
genai_processors/contrib/openrouter_model.py
genai_processors/core/README.md
genai_processors/core/__init__.py
genai_processors/core/adk.py
genai_processors/core/audio_io.py
genai_processors/core/constrained_decoding.py
genai_processors/core/drive.py
genai_processors/core/event_detection.py
genai_processors/core/filesystem.py
genai_processors/core/function_calling.py
genai_processors/core/genai_model.py
genai_processors/core/github.py
genai_processors/core/jinja_template.py
genai_processors/core/live_model.py
genai_processors/core/ollama_model.py
genai_processors/core/pdf.py
genai_processors/core/preamble.py
genai_processors/core/rate_limit_audio.py
genai_processors/core/realtime.py
genai_processors/core/speech_to_text.py
genai_processors/core/text.py
genai_processors/core/text_to_speech.py
genai_processors/core/timestamp.py
genai_processors/core/transformers_model.py
genai_processors/core/video.py
genai_processors/core/web.py
genai_processors/core/window.py
genai_processors/examples/README.md
genai_processors/examples/__init__.py
genai_processors/examples/chat.py
genai_processors/examples/live_simple_cli.py
genai_processors/examples/models.py
genai_processors/examples/pdf_cli.py
genai_processors/examples/realtime_simple_cli.py
genai_processors/examples/speech_to_text_cli.py
genai_processors-1.1.1.dist-info/licenses/LICENSE
genai_processors-1.1.1.dist-info/WHEEL
genai_processors-1.1.1.dist-info/METADATA
genai_processors-1.1.1.dist-info/RECORD
